eporner_api/__init__.py
eporner_api/eporner_api.py
eporner_api/modules/__init__.py
eporner_api/modules/consts.py
eporner_api/modules/errors.py
eporner_api/modules/locals.py
eporner_api/modules/progressbar.py
eporner_api/modules/sorting.py
eporner_api/tests/__init__.py
eporner_api/tests/test_category.py
eporner_api/tests/test_pornstar.py
eporner_api/tests/test_search.py
eporner_api/tests/test_video.py
eporner_api-1.9.2.dist-info/licenses/LICENSE
eporner_api-1.9.2.dist-info/METADATA
eporner_api-1.9.2.dist-info/WHEEL
eporner_api-1.9.2.dist-info/entry_points.txt
eporner_api-1.9.2.dist-info/top_level.txt
eporner_api-1.9.2.dist-info/RECORD
